opendap_downloader/__init__.py
opendap_downloader/opendap_downloader.py
opendap_downloader-0.9.0.dist-info/LICENSE
opendap_downloader-0.9.0.dist-info/METADATA
opendap_downloader-0.9.0.dist-info/WHEEL
opendap_downloader-0.9.0.dist-info/entry_points.txt
opendap_downloader-0.9.0.dist-info/top_level.txt
opendap_downloader-0.9.0.dist-info/RECORD
