Metadata-Version: 2.1
Name: opendap-downloader
Version: 0.9.0
Summary: Facilitate OPeNDAP download
Home-page: https://gitlab.mercator-ocean.fr/mercator/oper/opendap-downloader
Author: Jonathan Brouillet
Author-email: jbrouillet@mercator-ocean.fr
License: BSD Licence
Project-URL: Repository, https://gitlab.mercator-ocean.fr/mercator/oper/opendap-downloader
Classifier: Development Status :: 4 - Beta
Classifier: Intended Audience :: Science/Research
Classifier: Topic :: Scientific/Engineering
Classifier: Environment :: Console
Classifier: Programming Language :: Python :: 3.9
Classifier: License :: OSI Approved :: BSD License
Requires-Python: >=3.8
License-File: LICENSE
Requires-Dist: xarray (>=2022.03.0)
Requires-Dist: dask (>=2022.06.1)
Requires-Dist: netcdf4 (>=1.5.8)
Requires-Dist: pydap (>=3.2.2)
Requires-Dist: requests (>=2.26.0)
Requires-Dist: click (>=8.0.3)
